gruntest/__init__.py
gruntest/client.py
gruntest/grunner.py
gruntest/loader.py
gruntest/parse.py
gruntest/schemas.py
gruntest-0.1.1.dist-info/WHEEL
gruntest-0.1.1.dist-info/METADATA
gruntest-0.1.1.dist-info/RECORD
